<?xml version="1.0" encoding="UTF-8"?>
<objects serializationModel="Studio.02.02.00">
	<object class="Workspace" id="{39497d94-ed0a-41b7-83eb-6503576c3fdc}">
		<relationship name="projectSettings">
			<destination>{4e6f43b6-2d6b-41c7-9062-65543bba8feb}</destination>
		</relationship>
	</object>
	<object class="ProjectSettings" id="{4e6f43b6-2d6b-41c7-9062-65543bba8feb}">
		<relationship name="activePlatform">
			<destination>{159904c1-54f2-407f-8944-248d6c97baa4}</destination>
		</relationship>
	</object>
</objects>
